{
  "type": "object",
  "properties": {
    "string": {
      "type": "string"
    },
    "boolean": {
      "type": "boolean",
      "description": "Boolean description as a tooltip"
    },
    "exampleRadioEnum": {
      "type": "string",
      "enum": ["One", "Two", "Three"]
    },
    "number": {
      "type": "number"
    },
    "integer": {
      "type": "integer"
    },
    "date": {
      "type": "string",
      "format": "date"
    },
    "time": {
      "type": "string",
      "format": "time"
    },
    "enum": {
      "type": "string",
      "enum": ["One", "Two", "Three"]
    },
    "comments": {
      "type": "array",
      "title": "Array",
      "items": {
        "type": "object",
        "properties": {
          "name": {
            "type": "string"
          }
        }
      }
    }
  }
}
